todo/__init__.py
todo/todo.py
todo_database-0.0.4.dist-info/LICENSE
todo_database-0.0.4.dist-info/METADATA
todo_database-0.0.4.dist-info/WHEEL
todo_database-0.0.4.dist-info/top_level.txt
todo_database-0.0.4.dist-info/RECORD
