Metadata-Version: 2.1
Name: todo-database
Version: 0.0.4
Summary: A todo database wrapper for DPL course
Home-page: https://github.com/romanesin/todo_database
Author: Roman Esin
Author-email: esinromanswift@gmail.com
License: UNKNOWN
Platform: UNKNOWN
Classifier: Programming Language :: Python :: 3
Classifier: License :: OSI Approved :: MIT License
Classifier: Operating System :: OS Independent
Requires-Python: >=3.7
License-File: LICENSE
